.travis.yml
CHANGES.rst
MANIFEST.in
Makefile
Plocktastic.png
README.rst
requirements.txt
setup.py
plock/__init__.py
plock/config.py
plock/install.py
plock/tests.py
plock.egg-info/PKG-INFO
plock.egg-info/SOURCES.txt
plock.egg-info/dependency_links.txt
plock.egg-info/entry_points.txt
plock.egg-info/not-zip-safe
plock.egg-info/requires.txt
plock.egg-info/top_level.txt