Metadata-Version: 1.1
Name: plock
Version: 0.6.1
Summary: Pip installs Plock. Plock installs Plone.
Home-page: https://github.com/plock/plock
Author: Alex Clark
Author-email: aclark@aclark.net
License: Whatever license Plone is
Keywords: buildout pip plone virtualenv zope
Platform: UNKNOWN
Classifier: Framework :: Plone :: 4.3
Classifier: Framework :: Plone :: 5.0
Classifier: Programming Language :: Python :: 2.7
